continuous_delivery_scripts/__init__.py
continuous_delivery_scripts/_version.py
continuous_delivery_scripts/assert_news.py
continuous_delivery_scripts/create_news_file.py
continuous_delivery_scripts/generate_docs.py
continuous_delivery_scripts/generate_news.py
continuous_delivery_scripts/get_config.py
continuous_delivery_scripts/get_version.py
continuous_delivery_scripts/language_specifics.py
continuous_delivery_scripts/license_files.py
continuous_delivery_scripts/report_third_party_ip.py
continuous_delivery_scripts/tag_and_release.py
continuous_delivery_scripts/plugins/BASIC.MD
continuous_delivery_scripts/plugins/CI.MD
continuous_delivery_scripts/plugins/GITHUB_ACTIONS.MD
continuous_delivery_scripts/plugins/GOLAND.MD
continuous_delivery_scripts/plugins/NOOP.MD
continuous_delivery_scripts/plugins/PYTHON.MD
continuous_delivery_scripts/plugins/__init__.py
continuous_delivery_scripts/plugins/basic.py
continuous_delivery_scripts/plugins/ci.py
continuous_delivery_scripts/plugins/docker.py
continuous_delivery_scripts/plugins/github_actions.py
continuous_delivery_scripts/plugins/golang.py
continuous_delivery_scripts/plugins/noop.py
continuous_delivery_scripts/plugins/python.py
continuous_delivery_scripts/spdx_report/__init__.py
continuous_delivery_scripts/spdx_report/spdx_dependency.py
continuous_delivery_scripts/spdx_report/spdx_document.py
continuous_delivery_scripts/spdx_report/spdx_file.py
continuous_delivery_scripts/spdx_report/spdx_helpers.py
continuous_delivery_scripts/spdx_report/spdx_package.py
continuous_delivery_scripts/spdx_report/spdx_project.py
continuous_delivery_scripts/spdx_report/spdx_summary.py
continuous_delivery_scripts/spdx_report/templates/third_party_IP_report.csv.jinja2
continuous_delivery_scripts/spdx_report/templates/third_party_IP_report.html.jinja2
continuous_delivery_scripts/spdx_report/templates/third_party_IP_report.txt.jinja2
continuous_delivery_scripts/utils/__init__.py
continuous_delivery_scripts/utils/aws_helpers.py
continuous_delivery_scripts-3.2.6.dist-info/licenses/LICENSE
continuous_delivery_scripts-3.2.6.dist-info/METADATA
continuous_delivery_scripts-3.2.6.dist-info/WHEEL
continuous_delivery_scripts-3.2.6.dist-info/entry_points.txt
continuous_delivery_scripts-3.2.6.dist-info/top_level.txt
continuous_delivery_scripts-3.2.6.dist-info/RECORD
