Metadata-Version: 2.4
Name: continuous-delivery-scripts
Version: 3.2.6
Summary: Continuous Delivery scripts to increase automation
Home-page: https://github.com/ARMmbed/continuous-delivery-scripts
Author: CMSIS team
Author-email: adrien.cabarbaye@arm.com
License: Apache 2.0
Keywords: Arm Tools CI CD Continuous Delivery Scripts Automation
Classifier: Intended Audience :: Developers
Classifier: License :: OSI Approved :: Apache Software License
Classifier: Programming Language :: Python
Classifier: Programming Language :: Python :: 3 :: Only
Classifier: Programming Language :: Python :: 3.8
Classifier: Programming Language :: Python :: 3.9
Classifier: Programming Language :: Python :: 3.10
Classifier: Programming Language :: Python :: 3.11
Classifier: Topic :: Software Development :: Build Tools
Requires-Python: >=3.8,<4
License-File: LICENSE
Requires-Dist: gitpython
Requires-Dist: towncrier==22.12.0
Requires-Dist: pyautoversion~=1.2.0
Requires-Dist: pdoc3==0.10.0
Requires-Dist: toml
Requires-Dist: semver~=2.13.0
Requires-Dist: python-dotenv
Requires-Dist: twine
Requires-Dist: boto3
Requires-Dist: packaging
Requires-Dist: licenseheaders<0.8.9
Requires-Dist: spdx-tools==0.6.1
Requires-Dist: license-expression
Requires-Dist: wcmatch
Requires-Dist: jellyfish
Requires-Dist: jinja2==2.11.3
Requires-Dist: dataclasses; python_version < "3.7"
Requires-Dist: markupsafe==2.0.1
Dynamic: author
Dynamic: author-email
Dynamic: classifier
Dynamic: description
Dynamic: description-content-type
Dynamic: home-page
Dynamic: keywords
Dynamic: license
Dynamic: license-file
Dynamic: requires-dist
Dynamic: requires-python
Dynamic: summary
